Metadata-Version: 2.1
Name: lib-dzne-filestreams
Version: 0.2.0
Summary: Libary for handling genetic sequences. 
Author-email: Johannes Horler <johannes.horler@dzne.de>
License: Copyright © 2022 Johannes Horler
Classifier: License :: OSI Approved :: MIT License
Classifier: Programming Language :: Python
Classifier: Programming Language :: Python :: 3
Requires-Python: >=3.11
License-File: LICENSE
Requires-Dist: tomli-w
Requires-Dist: lib-dzne-basetables (>=0.1.2)
Requires-Dist: lib-dzne-tsv (>=0.1.4)
Requires-Dist: lib-dzne-workbook (>=0.1.3)
Requires-Dist: lib-dzne-seq (>=0.2.0)
